[
    {
        "number": "0",
        "name": "Kevin",
        "active": "true",
        "attemptedFG": [
            {
                "x": "44.5",
                "y": "-255",
                "made": "true",
                "assistedBy": ""
            }
        ],
        "attemptedFT": [],
        "rebounds": "1",
        "assists": "0",
        "steals": "0",
        "blocks": "0",
        "turnovers": "0",
        "fouls": "0"
    },
    {
        "number": "3",
        "name": "Edmond",
        "active": "true",
        "attemptedFG": [],
        "attemptedFT": [],
        "rebounds": "0",
        "assists": "0",
        "steals": "0",
        "blocks": "0",
        "turnovers": "0",
        "fouls": "0"
    },
    {
        "number": "4",
        "name": "David",
        "active": "true",
        "attemptedFG": [],
        "attemptedFT": [],
        "rebounds": "0",
        "assists": "0",
        "steals": "0",
        "blocks": "0",
        "turnovers": "0",
        "fouls": "0"
    },
    {
        "number": "5",
        "name": "Christian",
        "active": "true",
        "attemptedFG": [],
        "attemptedFT": [],
        "rebounds": "0",
        "assists": "0",
        "steals": "0",
        "blocks": "0",
        "turnovers": "0",
        "fouls": "0"
    },
    {
        "number": "10",
        "name": "Jisu",
        "active": "true",
        "attemptedFG": [],
        "attemptedFT": [],
        "rebounds": "0",
        "assists": "0",
        "steals": "0",
        "blocks": "0",
        "turnovers": "0",
        "fouls": "0"
    },
    {
        "number": "11",
        "name": "Austin",
        "active": "false",
        "attemptedFG": [],
        "attemptedFT": [],
        "rebounds": "0",
        "assists": "0",
        "steals": "0",
        "blocks": "0",
        "turnovers": "0",
        "fouls": "0"
    },
    {
        "number": "13",
        "name": "Charles",
        "active": "false",
        "attemptedFG": [],
        "attemptedFT": [],
        "rebounds": "0",
        "assists": "0",
        "steals": "0",
        "blocks": "0",
        "turnovers": "0",
        "fouls": "0"
    },
    {
        "number": "22",
        "name": "Paul",
        "active": "false",
        "attemptedFG": [],
        "attemptedFT": [],
        "rebounds": "0",
        "assists": "0",
        "steals": "0",
        "blocks": "0",
        "turnovers": "0",
        "fouls": "0"
    },
    {
        "number": "23",
        "name": "Amos",
        "active": "false",
        "attemptedFG": [],
        "attemptedFT": [],
        "rebounds": "0",
        "assists": "0",
        "steals": "0",
        "blocks": "0",
        "turnovers": "0",
        "fouls": "0"
    },
    {
        "number": "31",
        "name": "Patrick",
        "active": "false",
        "attemptedFG": [],
        "attemptedFT": [],
        "rebounds": "0",
        "assists": "0",
        "steals": "0",
        "blocks": "0",
        "turnovers": "0",
        "fouls": "0"
    },
    {
        "number": "66",
        "name": "Bryan",
        "active": "false",
        "attemptedFG": [],
        "attemptedFT": [],
        "rebounds": "0",
        "assists": "0",
        "steals": "0",
        "blocks": "0",
        "turnovers": "0",
        "fouls": "0"
    }
]